nats_worker/__init__.py
nats_worker/core.py
nats_py_worker-0.0.9.dist-info/LICENSE
nats_py_worker-0.0.9.dist-info/METADATA
nats_py_worker-0.0.9.dist-info/WHEEL
nats_py_worker-0.0.9.dist-info/top_level.txt
nats_py_worker-0.0.9.dist-info/RECORD
