Metadata-Version: 2.1
Name: nats-py-worker
Version: 0.0.9
Summary: An opinionated utility for using NATS as a worker queue with NATS.py
License: Copyright (c) 2023 The University of Adelaide
Classifier: Development Status :: 2 - Pre-Alpha
Classifier: Intended Audience :: Developers
Classifier: License :: OSI Approved :: MIT License
Classifier: Operating System :: POSIX :: Linux
Classifier: Programming Language :: Python :: 3
Classifier: Programming Language :: Python :: 3.9
Classifier: Programming Language :: Python :: 3.10
Classifier: Programming Language :: Python :: 3.11
Classifier: Programming Language :: Python :: 3 :: Only
Requires-Python: >=3.9
License-File: LICENSE
Requires-Dist: nats-py >=2.4.0
